asyncclick/__init__.py
asyncclick/_compat.py
asyncclick/_termui_impl.py
asyncclick/_textwrap.py
asyncclick/_utils.py
asyncclick/_winconsole.py
asyncclick/core.py
asyncclick/decorators.py
asyncclick/exceptions.py
asyncclick/formatting.py
asyncclick/globals.py
asyncclick/parser.py
asyncclick/py.typed
asyncclick/shell_completion.py
asyncclick/termui.py
asyncclick/testing.py
asyncclick/types.py
asyncclick/utils.py
asyncclick-8.3.0.6.dist-info/licenses/LICENSE.txt
asyncclick-8.3.0.6.dist-info/WHEEL
asyncclick-8.3.0.6.dist-info/METADATA
asyncclick-8.3.0.6.dist-info/RECORD
