Metadata-Version: 2.4
Name: asyncclick
Version: 8.3.0.6
Summary: Composable command line interface toolkit, async fork
Maintainer-email: Matthias Urlichs <matthias@urlichs.de>
Requires-Python: >=3.11
License-Expression: BSD-3-Clause
Classifier: Development Status :: 5 - Production/Stable
Classifier: Intended Audience :: Developers
Classifier: Operating System :: OS Independent
Classifier: Programming Language :: Python
Classifier: Typing :: Typed
License-File: LICENSE.txt
Requires-Dist: colorama; platform_system == 'Windows'
Project-URL: Source, https://github.com/python-trio/asyncclick/
